{
  "BORDER_COLOR_GREY_LIGHTEST": "rgb(247, 247, 247)",
  "BORDER_COLOR_BRAND_SECONDARY_LIGHT": "rgb(219, 239, 255)",
  "BORDER_COLOR_GREY_LIGHT": "rgb(204, 204, 204)",
  "BORDER_COLOR_GREY_DARK": "rgb(106, 106, 106)",
  "BORDER_COLOR_BRAND_SECONDARY_DARK": "rgb(0, 0, 0)",
  "BORDER_COLOR_BRAND_SECONDARY": "rgb(178, 221, 255)",
  "BORDER_COLOR_GREY": "rgb(140, 140, 140)",
  "BORDER_COLOR_BRAND_PRIMARY_LIGHT": "rgb(236, 28, 36)",
  "BORDER_COLOR_WHITE": "rgb(255, 255, 255)",
  "BORDER_COLOR_BRAND_PRIMARY_DARK": "rgb(236, 28, 36)",
  "BORDER_COLOR_BRAND_PRIMARY": "rgb(0, 93, 164)",
  "BACKGROUND_COLOR_GREY_LIGHT": "rgb(204, 204, 204)",
  "BACKGROUND_COLOR_GREY_LIGHTEST": "rgb(247, 247, 247)",
  "BACKGROUND_COLOR_BRAND_SECONDARY_DARK": "rgb(0, 0, 0)",
  "BACKGROUND_COLOR_BRAND_SECONDARY_LIGHT": "rgb(219, 239, 255)",
  "BACKGROUND_COLOR_GREY_DARK": "rgb(106, 106, 106)",
  "BACKGROUND_COLOR_GREY": "rgb(140, 140, 140)",
  "BACKGROUND_COLOR_BODY": "rgb(255, 255, 255)",
  "BACKGROUND_COLOR_BRAND_SECONDARY": "rgb(178, 221, 255)",
  "BACKGROUND_COLOR_BLACK": "rgb(0, 0, 0)",
  "BACKGROUND_COLOR_BRAND_PRIMARY_LIGHT": "rgb(236, 28, 36)",
  "BACKGROUND_COLOR_BRAND_PRIMARY_DARK": "rgb(236, 28, 36)",
  "BACKGROUND_COLOR_WHITE": "rgb(255, 255, 255)",
  "BACKGROUND_COLOR_BRAND_PRIMARY": "rgb(0, 93, 164)",
  "BACKGROUND_COLOR_GREY_DARKEST": "rgb(50, 50, 50)",
  "COLOR_BRAND_SECONDARY": "rgb(178, 221, 255)",
  "COLOR_BLACK": "rgb(0, 0, 0)",
  "COLOR_BRAND_PRIMARY_LIGHT": "rgb(236, 28, 36)",
  "COLOR_BRAND_PRIMARY_DARK": "rgb(236, 28, 36)",
  "COLOR_WHITE": "rgb(255, 255, 255)",
  "COLOR_BRAND_PRIMARY": "rgb(0, 93, 164)",
  "COLOR_GREY_LIGHT": "rgb(230, 230, 230)",
  "COLOR_BRAND_SECONDARY_DARK": "rgb(0, 0, 0)",
  "COLOR_BRAND_SECONDARY_LIGHT": "rgb(219, 239, 255)",
  "COLOR_GREY_DARK": "rgb(106, 106, 106)",
  "COLOR_GREY": "rgb(140, 140, 140)",
  "FONT_FAMILY_PRIMARY_FANCY": "'Argent CF', serif",
  "FONT_FAMILY_PRIMARY": "Georgia, serif",
  "FONT_FAMILY_SECONDARY_FANCY": "'PT Sans', sans-serif",
  "FONT_FAMILY_SECONDARY": "'Helvetica Neue', Helvetica, Arial, sans-serif",
  "FONT_FAMILY_BODY": "Georgia, serif",
  "FONT_FAMILY_BASIC": "Helvetica, sans-serif",
  "FONT_WEIGHT_LIGHT": "300",
  "FONT_WEIGHT_NORMAL": "400",
  "FONT_WEIGHT_BOLD": "700",
  "LINE_HEIGHT_SMALL": "1.1",
  "LINE_HEIGHT_NORMAL": "1.35",
  "LINE_HEIGHT_COPY": "1.5",
  "LINE_HEIGHT_LARGE": "1.85",
  "SPACING_00": "0",
  "SPACING_025": "0.25rem",
  "SPACING_050": "0.5rem",
  "SPACING_075": "0.75rem",
  "SPACING_1": "1rem",
  "SPACING_125": "1.25rem",
  "SPACING_150": "1.5rem",
  "SPACING_2": "2rem",
  "PRIMARY_XL_FONT_SIZE_DESKTOP": "58px",
  "PRIMARY_L_FONT_SIZE_MOBILE": "34px",
  "BODY_S_FONT_SIZE_DESKTOP": "initial",
  "PRIMARY_S_FONT_SIZE_DESKTOP": "36px",
  "PRIMARY_XXS_FONT_SIZE_DESKTOP": "24px",
  "ACCENT_L_FONT_SIZE_DESKTOP": "58px",
  "ACCENT_M_FONT_SIZE_DESKTOP": "initial",
  "PRIMARY_XXXS_FONT_SIZE_DESKTOP": "20px",
  "PRIMARY_XS_FONT_SIZE_DESKTOP": "26px",
  "SECONDARY_S_FONT_SIZE_MOBILE": "11px",
  "ACCENT_REGULAR_XXS_FONT_SIZE_DESKTOP": "18px",
  "SECONDARY_M_FONT_SIZE_MOBILE": "11px",
  "ACCENT_XXS_FONT_SIZE_DESKTOP": "18px",
  "ACCENT_S_FONT_SIZE_DESKTOP": "initial",
  "SECONDARY_REGULAR_M_FONT_SIZE_DESKTOP": "initial",
  "SECONDARY_L_FONT_SIZE_MOBILE": "17px",
  "SECONDARY_L_FONT_SIZE_DESKTOP": "30px",
  "SECONDARY_REGULAR_M_FONT_SIZE_MOBILE": "15px",
  "ACCENT_XXS_FONT_SIZE_MOBILE": "14px",
  "SECONDARY_M_FONT_SIZE_DESKTOP": "14px",
  "ACCENT_S_FONT_SIZE_MOBILE": "23px",
  "ACCENT_REGULAR_XXS_FONT_SIZE_MOBILE": "14px",
  "PRIMARY_XS_FONT_SIZE_MOBILE": "18px",
  "PRIMARY_XXXS_FONT_SIZE_MOBILE": "19px",
  "ACCENT_M_FONT_SIZE_MOBILE": "26px",
  "SECONDARY_S_FONT_SIZE_DESKTOP": "12px",
  "ACCENT_L_FONT_SIZE_MOBILE": "40px",
  "PRIMARY_XXS_FONT_SIZE_MOBILE": "22px",
  "PRIMARY_S_FONT_SIZE_MOBILE": "23px",
  "BODY_S_FONT_SIZE_MOBILE": "16px",
  "PRIMARY_L_FONT_SIZE_DESKTOP": "45px",
  "PRIMARY_XL_FONT_SIZE_MOBILE": "37px",
  "ACCENT_XS_FONT_SIZE_MOBILE": "18px",
  "PRIMARY_M_FONT_SIZE_MOBILE": "32px",
  "BODY_M_FONT_SIZE_DESKTOP": "initial",
  "BODY_M_FONT_SIZE_MOBILE": "18px",
  "PRIMARY_M_FONT_SIZE_DESKTOP": "36px",
  "ACCENT_XS_FONT_SIZE_DESKTOP": "23px",
  "SECONDARY_S_LETTER_SPACING_MOBILE": "normal",
  "SECONDARY_M_LETTER_SPACING_DESKTOP": "normal",
  "SECONDARY_L_LETTER_SPACING_DESKTOP": "normal",
  "PRIMARY_L_LETTER_SPACING_MOBILE": "normal",
  "SECONDARY_REGULAR_M_LETTER_SPACING_DESKTOP": "normal",
  "ACCENT_XS_LETTER_SPACING_MOBILE": "0.52px",
  "ACCENT_S_LETTER_SPACING_DESKTOP": "normal",
  "ACCENT_XXS_LETTER_SPACING_DESKTOP": ".52px",
  "BODY_M_LETTER_SPACING_MOBILE": "normal",
  "PRIMARY_M_LETTER_SPACING_MOBILE": "normal",
  "PRIMARY_XL_LETTER_SPACING_MOBILE": "normal",
  "ACCENT_REGULAR_XXS_LETTER_SPACING_DESKTOP": "0.52px",
  "BODY_S_LETTER_SPACING_MOBILE": "normal",
  "PRIMARY_S_LETTER_SPACING_MOBILE": "normal",
  "PRIMARY_XS_LETTER_SPACING_DESKTOP": "normal",
  "PRIMARY_XXS_LETTER_SPACING_MOBILE": "normal",
  "PRIMARY_XXXS_LETTER_SPACING_DESKTOP": "normal",
  "ACCENT_M_LETTER_SPACING_DESKTOP": "normal",
  "ACCENT_L_LETTER_SPACING_DESKTOP": "1.66px",
  "ACCENT_L_LETTER_SPACING_MOBILE": "1.14px",
  "ACCENT_M_LETTER_SPACING_MOBILE": ".74px",
  "PRIMARY_XXXS_LETTER_SPACING_MOBILE": "normal",
  "PRIMARY_XXS_LETTER_SPACING_DESKTOP": "normal",
  "PRIMARY_XS_LETTER_SPACING_MOBILE": "normal",
  "PRIMARY_S_LETTER_SPACING_DESKTOP": "normal",
  "BODY_S_LETTER_SPACING_DESKTOP": "normal",
  "ACCENT_REGULAR_XXS_LETTER_SPACING_MOBILE": "0.4px",
  "PRIMARY_XL_LETTER_SPACING_DESKTOP": "normal",
  "ACCENT_XS_LETTER_SPACING_DESKTOP": "0.66px",
  "ACCENT_XXS_LETTER_SPACING_MOBILE": ".4px",
  "PRIMARY_M_LETTER_SPACING_DESKTOP": "normal",
  "BODY_M_LETTER_SPACING_DESKTOP": "normal",
  "ACCENT_S_LETTER_SPACING_MOBILE": ".66px",
  "SECONDARY_REGULAR_M_LETTER_SPACING_MOBILE": "normal",
  "PRIMARY_L_LETTER_SPACING_DESKTOP": "normal",
  "SECONDARY_L_LETTER_SPACING_MOBILE": "normal",
  "SECONDARY_M_LETTER_SPACING_MOBILE": "normal",
  "SECONDARY_S_LETTER_SPACING_DESKTOP": "normal",
  "PRIMARY_XS_FONT_WEIGHT_MOBILE": "700",
  "PRIMARY_XXXS_FONT_WEIGHT_MOBILE": "700",
  "ACCENT_M_FONT_WEIGHT_MOBILE": "300",
  "ACCENT_REGULAR_XXS_FONT_WEIGHT_DESKTOP": "initial",
  "ACCENT_L_FONT_WEIGHT_MOBILE": "300",
  "PRIMARY_XXS_FONT_WEIGHT_MOBILE": "700",
  "PRIMARY_S_FONT_WEIGHT_MOBILE": "700",
  "BODY_S_FONT_WEIGHT_MOBILE": "initial",
  "ACCENT_XXS_FONT_WEIGHT_DESKTOP": "initial",
  "ACCENT_S_FONT_WEIGHT_DESKTOP": "initial",
  "SECONDARY_REGULAR_M_FONT_WEIGHT_DESKTOP": "initial",
  "PRIMARY_XL_FONT_WEIGHT_MOBILE": "700",
  "SECONDARY_L_FONT_WEIGHT_DESKTOP": "initial",
  "BODY_M_FONT_WEIGHT_MOBILE": "initial",
  "ACCENT_XS_FONT_WEIGHT_MOBILE": "300",
  "SECONDARY_M_FONT_WEIGHT_DESKTOP": "initial",
  "PRIMARY_M_FONT_WEIGHT_MOBILE": "700",
  "PRIMARY_L_FONT_WEIGHT_MOBILE": "700",
  "SECONDARY_S_FONT_WEIGHT_DESKTOP": "initial",
  "SECONDARY_S_FONT_WEIGHT_MOBILE": "600",
  "PRIMARY_L_FONT_WEIGHT_DESKTOP": "700",
  "BODY_M_FONT_WEIGHT_DESKTOP": "initial",
  "PRIMARY_M_FONT_WEIGHT_DESKTOP": "700",
  "ACCENT_XS_FONT_WEIGHT_DESKTOP": "initial",
  "SECONDARY_M_FONT_WEIGHT_MOBILE": "600",
  "PRIMARY_XL_FONT_WEIGHT_DESKTOP": "700",
  "SECONDARY_L_FONT_WEIGHT_MOBILE": "600",
  "SECONDARY_REGULAR_M_FONT_WEIGHT_MOBILE": "initial",
  "ACCENT_S_FONT_WEIGHT_MOBILE": "300",
  "ACCENT_XXS_FONT_WEIGHT_MOBILE": "300",
  "BODY_S_FONT_WEIGHT_DESKTOP": "initial",
  "PRIMARY_S_FONT_WEIGHT_DESKTOP": "700",
  "PRIMARY_XXS_FONT_WEIGHT_DESKTOP": "700",
  "ACCENT_REGULAR_XXS_FONT_WEIGHT_MOBILE": "400",
  "ACCENT_L_FONT_WEIGHT_DESKTOP": "initial",
  "ACCENT_M_FONT_WEIGHT_DESKTOP": "initial",
  "PRIMARY_XXXS_FONT_WEIGHT_DESKTOP": "700",
  "PRIMARY_XS_FONT_WEIGHT_DESKTOP": "700",
  "ACCENT_XS_LINE_HEIGHT_DESKTOP": "24px",
  "BODY_M_LINE_HEIGHT_DESKTOP": "initial",
  "PRIMARY_M_LINE_HEIGHT_DESKTOP": "40px",
  "PRIMARY_XL_LINE_HEIGHT_DESKTOP": "57px",
  "PRIMARY_S_LINE_HEIGHT_DESKTOP": "38px",
  "PRIMARY_XXS_LINE_HEIGHT_DESKTOP": "27px",
  "SECONDARY_S_LINE_HEIGHT_MOBILE": "14px",
  "BODY_S_LINE_HEIGHT_DESKTOP": "initial",
  "ACCENT_L_LINE_HEIGHT_DESKTOP": "50px",
  "PRIMARY_XXXS_LINE_HEIGHT_DESKTOP": "23px",
  "PRIMARY_XS_LINE_HEIGHT_DESKTOP": "29px",
  "ACCENT_M_LINE_HEIGHT_DESKTOP": "initial",
  "ACCENT_REGULAR_XXS_LINE_HEIGHT_DESKTOP": "26px",
  "SECONDARY_M_LINE_HEIGHT_MOBILE": "15px",
  "SECONDARY_L_LINE_HEIGHT_MOBILE": "21px",
  "ACCENT_S_LINE_HEIGHT_DESKTOP": "initial",
  "ACCENT_XXS_LINE_HEIGHT_DESKTOP": "18px",
  "SECONDARY_REGULAR_M_LINE_HEIGHT_MOBILE": "15px",
  "SECONDARY_REGULAR_M_LINE_HEIGHT_DESKTOP": "initial",
  "ACCENT_S_LINE_HEIGHT_MOBILE": "23px",
  "ACCENT_XXS_LINE_HEIGHT_MOBILE": "0.4px",
  "SECONDARY_L_LINE_HEIGHT_DESKTOP": "35px",
  "SECONDARY_M_LINE_HEIGHT_DESKTOP": "17px",
  "ACCENT_REGULAR_XXS_LINE_HEIGHT_MOBILE": "14px",
  "PRIMARY_XS_LINE_HEIGHT_MOBILE": "21px",
  "PRIMARY_XXXS_LINE_HEIGHT_MOBILE": "21px",
  "ACCENT_M_LINE_HEIGHT_MOBILE": "26px",
  "ACCENT_L_LINE_HEIGHT_MOBILE": "36px",
  "SECONDARY_S_LINE_HEIGHT_DESKTOP": "17px",
  "PRIMARY_XXS_LINE_HEIGHT_MOBILE": "23px",
  "PRIMARY_S_LINE_HEIGHT_MOBILE": "28px",
  "BODY_S_LINE_HEIGHT_MOBILE": "22px",
  "PRIMARY_XL_LINE_HEIGHT_MOBILE": "37px",
  "PRIMARY_M_LINE_HEIGHT_MOBILE": "35px",
  "BODY_M_LINE_HEIGHT_MOBILE": "24px",
  "ACCENT_XS_LINE_HEIGHT_MOBILE": "19px",
  "PRIMARY_L_LINE_HEIGHT_DESKTOP": "42px",
  "PRIMARY_L_LINE_HEIGHT_MOBILE": "31px",
  "FONT_FAMILY_ACCENT": "'Helvetica Neue', Helvetica, Arial, sans-serif",
  "FONT_FAMILY_ACCENT_FANCY": "'Teko', 'Open Sans', sans-serif",
  "BACKGROUND_COLOR_BRAND_ACCENT": "rgb(251, 75, 34)",
  "BORDER_COLOR_BRAND_ACCENT": "rgb(251, 75, 34)",
  "COLOR_BRAND_ACCENT": "rgb(251, 75, 34)"
}