{
	"imports": [
		"../base/all.json"
	],
	"props": {
		"BACKGROUND_COLOR_BRAND_PRIMARY": {
			"value": "{!YELLOW_59}",
			"type": "color",
			"category": "background-color"
		},
		"BORDER_COLOR_BRAND_PRIMARY": {
			"value": "{!YELLOW_59}",
			"type": "color",
			"category": "hr-color"
		},
		"COLOR_BRAND_PRIMARY": {
			"value": "{!YELLOW_59}",
			"type": "color",
			"category": "text-color"
		},
		"BACKGROUND_COLOR_BRAND_SECONDARY": {
			"value": "{!RED_39}",
			"type": "color",
			"category": "background-color"
		},
		"BORDER_COLOR_BRAND_SECONDARY": {
			"value": "{!RED_39}",
			"type": "color",
			"category": "hr-color"
		},
		"COLOR_BRAND_SECONDARY": {
			"value": "{!RED_39}",
			"type": "color",
			"category": "text-color"
		},
		"COLOR_BRAND_ACCENT": {
			"value": "{!BLACK_6}",
			"type": "color",
			"category": "text-color"
		},
		"BORDER_COLOR_BRAND_ACCENT": {
			"value": "{!BLACK_6}",
			"type": "color",
			"category": "hr-color"
		},
		"BACKGROUND_COLOR_BRAND_ACCENT": {
			"value": "{!BLACK_6}",
			"type": "color",
			"category": "background-color"
		},
		"COLOR_GREY_LIGHTEST": {
			"value": "{!GREY_94}",
			"type": "color",
			"category": "text-color"
		},
		"BORDER_COLOR_GREY_LIGHTEST": {
			"value": "{!GREY_94}",
			"type": "color",
			"category": "hr-color"
		},
		"BACKGROUND_COLOR_GREY_LIGHTEST": {
			"value": "{!GREY_94}",
			"type": "color",
			"category": "background-color"
		},
		"COLOR_GREY_LIGHT": {
			"value": "{!GREY_86}",
			"type": "color",
			"category": "text-color"
		},
		"BORDER_COLOR_GREY_LIGHT": {
			"value": "{!GREY_86}",
			"type": "color",
			"category": "hr-color"
		},
		"BACKGROUND_COLOR_GREY_LIGHT": {
			"value": "{!GREY_86}",
			"type": "color",
			"category": "background-color"
		},
		"COLOR_GREY_DARK": {
			"value": "{!GREY_36}",
			"type": "color",
			"category": "text-color"
		},
		"BORDER_COLOR_GREY_DARK": {
			"value": "{!GREY_36}",
			"type": "color",
			"category": "hr-color"
		},
		"BACKGROUND_COLOR_GREY_DARK": {
			"value": "{!GREY_36}",
			"type": "color",
			"category": "background-color"
		},
		"FONT_FAMILY_PRIMARY_FANCY": {
			"value": "{!AILERON}",
			"type": "font-family",
			"category": "font-family",
			"comment": "The webfont for font-family-primary."
		},
		"FONT_FAMILY_PRIMARY": {
			"value": "{!HELVETICA}",
			"type": "font-family",
			"category": "font-family",
			"comment": "The fallback font for font-family-primary."
		},
		"FONT_FAMILY_SECONDARY_FANCY": {
			"value": "{!ACUMIN_PRO_WIDE}",
			"type": "font-family",
			"category": "font-family",
			"comment": "Available via Typekit."
		},
		"FONT_FAMILY_SECONDARY": {
			"value": "{!HELVETICA}",
			"type": "font-family",
			"category": "font-family",
			"comment": "Fallback from secondary-fancy"
		},
		"FONT_FAMILY_BODY": {
			"value": "{!HELVETICA}",
			"type": "font-family",
			"category": "font-family"
		},
		"FONT_FAMILY_BASIC": {
			"value": "{!HELVETICA}",
			"type": "font-family",
			"category": "font-family"
		},
		"FONT_FAMILY_ACCENT": {
			"value": "Helvetica, sans-serif",
			"type": "font-family",
			"category": "font-family",
			"comment": "The fallback for the accent font"
		},
		"FONT_FAMILY_ACCENT_FANCY": {
			"value": "'Brunel Deck', Helvetica, sans-serif",
			"type": "font-family",
			"category": "font-family",
			"comment": "The accent webfont, loaded async"
		}
	}
}
